ezpz/__init__.py
ezpz/main.py
ezpz-0.1.2.dist-info/DESCRIPTION.rst
ezpz-0.1.2.dist-info/METADATA
ezpz-0.1.2.dist-info/RECORD
ezpz-0.1.2.dist-info/WHEEL
ezpz-0.1.2.dist-info/entry_points.txt
ezpz-0.1.2.dist-info/metadata.json
ezpz-0.1.2.dist-info/top_level.txt
