Metadata-Version: 2.0
Name: ezpz
Version: 0.1.2
Summary: Easy pan-zoom crop-resizing
Home-page: https://github.com/pelmers/ezpz
Author: Peter Elmers
Author-email: peter.elmers@yahoo.com
License: all lefts reservered
Keywords: photography imagemagick timelapse
Platform: UNKNOWN
Classifier: Development Status :: 4 - Beta
Classifier: Intended Audience :: End Users/Desktop
Classifier: Topic :: Multimedia :: Graphics
Classifier: License :: OSI Approved :: MIT License
Classifier: Programming Language :: Python :: 2
Classifier: Programming Language :: Python :: 2.6
Classifier: Programming Language :: Python :: 2.7
Classifier: Programming Language :: Python :: 3
Classifier: Programming Language :: Python :: 3.3
Classifier: Programming Language :: Python :: 3.4
Classifier: Programming Language :: Python :: 3.5
Requires-Dist: wand
